repulsiveruby/__init__.py
repulsiveruby/__main__.py
repulsiveruby/controls.py
repulsiveruby/physics.py
repulsiveruby/resources.py
repulsiveruby/sprites.py
repulsiveruby/images/GameIcon.ico
repulsiveruby/images/background.png
repulsiveruby/images/ball1.png
repulsiveruby/images/ball2.png
repulsiveruby/images/ball3.png
repulsiveruby/images/ball_main.png
repulsiveruby/images/icon.png
repulsiveruby/images/intro.png
repulsiveruby/images/lose.png
repulsiveruby/sounds/collide.wav
repulsiveruby/sounds/music.wav
repulsiveruby-2.1.5.dist-info/LICENSE
repulsiveruby-2.1.5.dist-info/METADATA
repulsiveruby-2.1.5.dist-info/WHEEL
repulsiveruby-2.1.5.dist-info/top_level.txt
repulsiveruby-2.1.5.dist-info/RECORD
