Metadata-Version: 2.1
Name: repulsiveruby
Version: 2.1.5
Summary: RepulsiveRuby: A game made with Pygame
Home-page: https://github.com/wq2012/RepulsiveRuby
Author: Quan Wang
Author-email: quanrpi@gmail.com
License: UNKNOWN
Platform: UNKNOWN
Classifier: Programming Language :: Python :: 3
Classifier: Programming Language :: Python :: 2.7
Classifier: License :: OSI Approved :: Apache Software License
Classifier: Operating System :: OS Independent
